turing_envs/__init__.py
turing_envs/import_fix.py
turing_envs/pong.py
turing_envs-0.1.1.dist-info/LICENSE
turing_envs-0.1.1.dist-info/METADATA
turing_envs-0.1.1.dist-info/WHEEL
turing_envs-0.1.1.dist-info/top_level.txt
turing_envs-0.1.1.dist-info/RECORD
